class_pool/__init__.py
class_pool/db.py
class_pool/drf.py
class_pool/pool.py
class_pool/version.py
class_pool-0.7rc1.dist-info/METADATA
class_pool-0.7rc1.dist-info/RECORD
class_pool-0.7rc1.dist-info/WHEEL
class_pool-0.7rc1.dist-info/top_level.txt
