Metadata-Version: 2.1
Name: class-pool
Version: 0.7rc1
Summary: Simple implementation of class pools for Python. Optional support for Django and DRF (if available)
Home-page: UNKNOWN
Author: Pawel Pecio
Author-email: 
License: UNKNOWN
Platform: UNKNOWN
Classifier: Programming Language :: Python :: 3
Classifier: License :: OSI Approved :: MIT License
Classifier: Operating System :: OS Independent
